setup.cfg
setup.py
reimegardsApp.egg-info/PKG-INFO
reimegardsApp.egg-info/SOURCES.txt
reimegardsApp.egg-info/dependency_links.txt
reimegardsApp.egg-info/entry_points.txt
reimegardsApp.egg-info/not-zip-safe
reimegardsApp.egg-info/top_level.txt
reimegardsapp/__init__.py