Metadata-Version: 1.0
Name: reimegardsApp
Version: 0.1dev
Summary: Reimegards App
Home-page: UNKNOWN
Author: Johan Reimegard
Author-email: johan.reimegard@scilifelab.se
License: GPLv3
Keywords: reimegard
Platform: UNKNOWN
